sailboat/__init__.py
sailboat/__main__.py
sailboat/autocomplete.py
sailboat/build.py
sailboat/builders.py
sailboat/core.py
sailboat/other.py
sailboat/plugins.json
sailboat/prerelease.py
sailboat/resources/brew.rb
sailboat/resources/dragdrop.png
sailboat/resources/gitignore.template
sailboat/resources/info.plist.xml
sailboat/resources/sailboat.yml.template
sailboat/resources/settings.py.template
sailboat/resources/setup.py.template
sailboat/resources/wixpy.template.json
sailboat-0.26.2.dist-info/LICENSE
sailboat-0.26.2.dist-info/METADATA
sailboat-0.26.2.dist-info/WHEEL
sailboat-0.26.2.dist-info/entry_points.txt
sailboat-0.26.2.dist-info/top_level.txt
sailboat-0.26.2.dist-info/RECORD
