Metadata-Version: 2.1
Name: sailboat
Version: 0.26.2
Summary: A quick and easy way to distribute your Python projects!
Home-page: https://github.com/cole-wilson/sailboat
Author: Cole Wilson
Author-email: cole@colewilson.xyz
License: MIT
Keywords: sail package python setup.py sailboat shipsnake distribute ship snake snek release build
Platform: UNKNOWN
Classifier: Programming Language :: Python :: 3
Requires-Python: >=3.6
Requires-Dist: toml
Requires-Dist: semver
Requires-Dist: requests
Requires-Dist: setuptools
Requires-Dist: twine
Requires-Dist: colorama
Requires-Dist: enlighten
Requires-Dist: blessed
